fave_syllabify/__init__.py
fave_syllabify/syllabify.py
fave_syllabify-0.1.3.dist-info/LICENSE
fave_syllabify-0.1.3.dist-info/WHEEL
fave_syllabify-0.1.3.dist-info/METADATA
fave_syllabify-0.1.3.dist-info/RECORD
