Metadata-Version: 2.1
Name: fave-syllabify
Version: 0.1.3
Summary: Syllabify force-aligned textgrids
License: GPLv3
Author: JoFrhwld
Author-email: JoFrhwld@gmail.com
Requires-Python: >=3.10,<4.0
Classifier: License :: Other/Proprietary License
Classifier: Programming Language :: Python :: 3
Classifier: Programming Language :: Python :: 3.10
Classifier: Programming Language :: Python :: 3.11
Requires-Dist: aligned-textgrid (>=0.6.6,<0.7.0)
